{
  "number": 50,
  "name": "سُورَةُ قٓ",
  "englishName": "Qaaf",
  "englishNameTranslation": "The letter Qaaf",
  "revelationType": "Meccan",
  "numberOfAyahs": 45,
  "ayahs": [
    {
      "number": 4631,
      "text": "[m[قٓ]‌ۚ وَ[h:5855[ٱ]لْقُرْءَانِ [h:12775[ٱ]لْمَج[p[ِي][q[د]ِ",
      "numberInSurah": 1,
      "juz": 26,
      "manzil": 7,
      "page": 518,
      "ruku": 452,
      "hizbQuarter": 207,
      "sajda": false
    },
    {
      "number": 4632,
      "text": "بَلْ عَجِب[o[ُوٓ][s[اْ] أَ[f:11468[ن ج][o[َا]ٓءَه[w:11469[ُم م]ُّ[f:6895[نذ]ِ[a:11470[رٌ م]ِّنْهُمْ فَقَالَ [h:12776[ٱ]لْكَ[n[ـٰ]فِرُونَ هَ[n[ـٰ]ذَا شَىْءٌ عَج[p[ِي][q[ب]ٌ",
      "numberInSurah": 2,
      "juz": 26,
      "manzil": 7,
      "page": 518,
      "ruku": 452,
      "hizbQuarter": 207,
      "sajda": false
    },
    {
      "number": 4633,
      "text": "أَءِذَا مِتْنَا وَكُ[g[نّ]َا تُرَا[f:12777[بًا‌ۖ ذ][n[َٲ]لِكَ رَ[q:12778[جْ][i:12779[عُۢ ب]َع[p[ِي][q[د]ٌ",
      "numberInSurah": 3,
      "juz": 26,
      "manzil": 7,
      "page": 518,
      "ruku": 452,
      "hizbQuarter": 207,
      "sajda": false
    },
    {
      "number": 4634,
      "text": "قَ[q:298[دْ] عَلِمْنَا مَا تَ[f:12780[نق]ُصُ [h:12781[ٱ]لْأَرْضُ مِنْهُمْ‌ۖ وَعِ[f:12782[ند]َنَا كِتَ[n[ـٰ]بٌ حَف[p[ِي]ظُۢ",
      "numberInSurah": 4,
      "juz": 26,
      "manzil": 7,
      "page": 518,
      "ruku": 452,
      "hizbQuarter": 207,
      "sajda": false
    },
    {
      "number": 4635,
      "text": "بَلْ كَذَّبُو[s[اْ] بِ[h:370[ٱ]لْحَقِّ لَ[g[مّ]َا ج[o[َا]ٓءَهُمْ فَهُمْ ف[o[ِىٓ] أَمْ[a:12783[رٍ م]َّر[p[ِي][q[ج]ٍ",
      "numberInSurah": 5,
      "juz": 26,
      "manzil": 7,
      "page": 518,
      "ruku": 452,
      "hizbQuarter": 207,
      "sajda": false
    },
    {
      "number": 4636,
      "text": "أَفَلَمْ يَ[f:5165[نظ]ُر[o[ُوٓ][s[اْ] إِلَى [h:157[ٱ][l[ل]سَّم[o[َا]ٓءِ فَوْقَهُمْ كَيْفَ بَنَيْنَ[n[ـٰ]هَا وَزَيَّ[g[نّ]َ[n[ـٰ]هَا وَمَا لَهَا مِ[f:12784[ن ف]ُر[p[ُو][q[ج]ٍ",
      "numberInSurah": 6,
      "juz": 26,
      "manzil": 7,
      "page": 518,
      "ruku": 452,
      "hizbQuarter": 207,
      "sajda": false
    },
    {
      "number": 4637,
      "text": "وَ[h:9999[ٱ]لْأَرْضَ مَدَ[q:7217[دْ]نَ[n[ـٰ]هَا وَأَلْقَيْنَا فِيهَا رَو[n[َٲ]سِىَ وَأَ[i:7218[نۢب]َتْنَا فِيهَا مِ[f:843[ن ك]ُلِّ زَوْ[i:8922[جِۭ ب]َه[p[ِي][q[ج]ٍ",
      "numberInSurah": 7,
      "juz": 26,
      "manzil": 7,
      "page": 518,
      "ruku": 452,
      "hizbQuarter": 207,
      "sajda": false
    },
    {
      "number": 4638,
      "text": "تَ[q:12785[بْ]صِرَ[a:12786[ةً و]َذِكْرَىٰ لِكُلِّ عَ[q:10938[بْ][a:10939[دٍ م]ُّن[p[ِي][q[ب]ٍ",
      "numberInSurah": 8,
      "juz": 26,
      "manzil": 7,
      "page": 518,
      "ruku": 452,
      "hizbQuarter": 207,
      "sajda": false
    },
    {
      "number": 4639,
      "text": "وَنَزَّلْنَا مِنَ [h:64[ٱ][l[ل]سَّم[o[َا]ٓءِ م[o[َا]ٓ[a:12787[ءً م]ُّبَ[n[ـٰ]رَ[f:12788[كًا ف]َأَ[i:9998[نۢب]َتْنَا بِه[n[ِۦ] جَ[g[نّ]َ[n[ـٰ][a:12789[تٍ و]َحَبَّ [h:12790[ٱ]لْحَص[p[ِي][q[د]ِ",
      "numberInSurah": 9,
      "juz": 26,
      "manzil": 7,
      "page": 518,
      "ruku": 452,
      "hizbQuarter": 207,
      "sajda": false
    },
    {
      "number": 4640,
      "text": "وَ[h:9999[ٱ][l[ل][g[نّ]َخْلَ بَاسِقَ[n[ـٰ][u:12791[تٍ ل]َّهَا طَلْ[a:12792[عٌ ن]َّض[p[ِي][q[د]ٌ",
      "numberInSurah": 10,
      "juz": 26,
      "manzil": 7,
      "page": 518,
      "ruku": 452,
      "hizbQuarter": 207,
      "sajda": false
    },
    {
      "number": 4641,
      "text": "رِّزْ[u:12793[قًا ل]ِّلْعِبَادِ‌ۖ وَأَحْيَيْنَا بِه[n[ِۦ] بَلْدَ[a:9661[ةً م]َّيْ[f:12206[تًا‌ۚ ك]َذ[n[َٲ]لِكَ [h:12794[ٱ]لْخُر[p[ُو][q[ج]ُ",
      "numberInSurah": 11,
      "juz": 26,
      "manzil": 7,
      "page": 518,
      "ruku": 452,
      "hizbQuarter": 207,
      "sajda": false
    },
    {
      "number": 4642,
      "text": "كَذَّبَتْ قَ[q:8394[بْ]لَهُمْ قَوْمُ نُو[a:12795[حٍ و]َأَصْحَ[n[ـٰ]بُ [h:12796[ٱ][l[ل]رَّسِّ وَثَم[p[ُو][q[د]ُ",
      "numberInSurah": 12,
      "juz": 26,
      "manzil": 7,
      "page": 518,
      "ruku": 452,
      "hizbQuarter": 207,
      "sajda": false
    },
    {
      "number": 4643,
      "text": "وَعَا[a:11490[دٌ و]َفِرْعَوْنُ وَإِخْو[n[َٲ]نُ ل[p[ُو][q[ط]ٍ",
      "numberInSurah": 13,
      "juz": 26,
      "manzil": 7,
      "page": 518,
      "ruku": 452,
      "hizbQuarter": 207,
      "sajda": false
    },
    {
      "number": 4644,
      "text": "وَأَصْحَ[n[ـٰ]بُ [h:12797[ٱ]لْأَيْكَةِ وَقَوْمُ تُبَّ[f:12798[عٍ‌ۚ ك]ُ[f:12799[لٌّ ك]َذَّبَ [h:11495[ٱ][l[ل]رُّسُلَ فَحَقَّ وَع[p[ِي][q[د]ِ",
      "numberInSurah": 14,
      "juz": 26,
      "manzil": 7,
      "page": 518,
      "ruku": 452,
      "hizbQuarter": 207,
      "sajda": false
    },
    {
      "number": 4645,
      "text": "أَفَعَيِينَا بِ[h:12800[ٱ]لْخَلْقِ [h:12801[ٱ]لْأَوَّلِ‌ۚ بَلْ هُمْ فِى لَ[q:12802[بْ][a:12803[سٍ م]ِّنْ خَلْ[f:6887[قٍ ج]َد[p[ِي][q[د]ٍ",
      "numberInSurah": 15,
      "juz": 26,
      "manzil": 7,
      "page": 518,
      "ruku": 452,
      "hizbQuarter": 207,
      "sajda": false
    },
    {
      "number": 4646,
      "text": "وَلَقَ[q:341[دْ] خَلَ[q:5159[قْ]نَا [h:7228[ٱ]لْإِ[f:5969[نس]َ[n[ـٰ]نَ وَنَعْلَمُ مَا تُوَسْوِسُ بِه[n[ِۦ] نَفْسُهُ[n[ۥ]‌ۖ وَنَحْنُ أَ[q:1355[قْ]رَبُ إِلَيْهِ مِنْ حَ[q:12804[بْ]لِ [h:12805[ٱ]لْوَر[p[ِي][q[د]ِ",
      "numberInSurah": 16,
      "juz": 26,
      "manzil": 7,
      "page": 519,
      "ruku": 453,
      "hizbQuarter": 207,
      "sajda": false
    },
    {
      "number": 4647,
      "text": "إِذْ يَتَلَقَّى [h:12806[ٱ]لْمُتَلَقِّيَانِ عَنِ [h:7424[ٱ]لْيَمِينِ وَعَنِ [h:12807[ٱ][l[ل]شِّمَالِ قَع[p[ِي][q[د]ٌ",
      "numberInSurah": 17,
      "juz": 26,
      "manzil": 7,
      "page": 519,
      "ruku": 453,
      "hizbQuarter": 207,
      "sajda": false
    },
    {
      "number": 4648,
      "text": "مَّا يَلْفِظُ مِ[f:12808[ن ق]َوْلٍ إِلَّا لَدَيْهِ رَقِيبٌ عَت[p[ِي][q[د]ٌ",
      "numberInSurah": 18,
      "juz": 26,
      "manzil": 7,
      "page": 519,
      "ruku": 453,
      "hizbQuarter": 207,
      "sajda": false
    },
    {
      "number": 4649,
      "text": "وَج[o[َا]ٓءَتْ سَكْرَةُ [h:12809[ٱ]لْمَوْتِ بِ[h:370[ٱ]لْحَقِّ‌ۖ ذ[n[َٲ]لِكَ مَا كُ[f:735[نت]َ مِنْهُ تَح[p[ِي][q[د]ُ",
      "numberInSurah": 19,
      "juz": 26,
      "manzil": 7,
      "page": 519,
      "ruku": 453,
      "hizbQuarter": 207,
      "sajda": false
    },
    {
      "number": 4650,
      "text": "وَنُفِخَ فِى [h:4185[ٱ][l[ل]صُّورِ‌ۚ ذ[n[َٲ]لِكَ يَوْمُ [h:12810[ٱ]لْوَع[p[ِي][q[د]ِ",
      "numberInSurah": 20,
      "juz": 26,
      "manzil": 7,
      "page": 519,
      "ruku": 453,
      "hizbQuarter": 207,
      "sajda": false
    },
    {
      "number": 4651,
      "text": "وَج[o[َا]ٓءَتْ كُلُّ نَفْ[a:12811[سٍ م]َّعَهَا س[o[َا]ٓئِ[a:12812[قٌ و]َشَه[p[ِي][q[د]ٌ",
      "numberInSurah": 21,
      "juz": 26,
      "manzil": 7,
      "page": 519,
      "ruku": 453,
      "hizbQuarter": 207,
      "sajda": false
    },
    {
      "number": 4652,
      "text": "لَّقَ[q:2389[دْ] كُ[f:735[نت]َ فِى غَفْلَ[a:8863[ةٍ م]ِّنْ هَ[n[ـٰ]ذَا فَكَشَفْنَا عَ[f:626[نك]َ غِط[o[َا]ٓءَكَ فَبَصَرُكَ [h:12813[ٱ]لْيَوْمَ حَد[p[ِي][q[د]ٌ",
      "numberInSurah": 22,
      "juz": 26,
      "manzil": 7,
      "page": 519,
      "ruku": 453,
      "hizbQuarter": 207,
      "sajda": false
    },
    {
      "number": 4653,
      "text": "وَقَالَ قَرِينُهُ[n[ۥ] هَ[n[ـٰ]ذَا مَا لَدَىَّ عَت[p[ِي][q[د]ٌ",
      "numberInSurah": 23,
      "juz": 26,
      "manzil": 7,
      "page": 519,
      "ruku": 453,
      "hizbQuarter": 207,
      "sajda": false
    },
    {
      "number": 4654,
      "text": "أَلْقِيَا فِى جَهَ[g[نّ]َمَ كُلَّ كَفَّارٍ عَن[p[ِي][q[د]ٍ",
      "numberInSurah": 24,
      "juz": 26,
      "manzil": 7,
      "page": 519,
      "ruku": 453,
      "hizbQuarter": 207,
      "sajda": false
    },
    {
      "number": 4655,
      "text": "مَّ[g[نّ]َا[u:12814[عٍ ل]ِّلْخَيْرِ مُعْتَ[a:12815[دٍ م]ُّر[p[ِي][q[ب]ٍ",
      "numberInSurah": 25,
      "juz": 26,
      "manzil": 7,
      "page": 519,
      "ruku": 453,
      "hizbQuarter": 207,
      "sajda": false
    },
    {
      "number": 4656,
      "text": "ٱلَّذِى جَعَلَ مَعَ [h:3975[ٱ]للَّهِ إِلَ[n[ـٰ]هًا ءَاخَرَ فَأَلْقِيَاهُ فِى [h:10442[ٱ]لْعَذَابِ [h:12816[ٱ][l[ل]شَّد[p[ِي][q[د]ِ",
      "numberInSurah": 26,
      "juz": 26,
      "manzil": 7,
      "page": 519,
      "ruku": 453,
      "hizbQuarter": 207,
      "sajda": false
    },
    {
      "number": 4657,
      "text": "۞ قَالَ قَرِينُهُ[n[ۥ] رَبَّنَا م[o[َآ] أَ[q:12817[طْ]غَيْتُهُ[n[ۥ] وَلَ[n[ـٰ]كِ[f:2006[ن ك]َانَ فِى ضَلَ[n[ـٰ][i:7043[لِۭ ب]َع[p[ِي][q[د]ٍ",
      "numberInSurah": 27,
      "juz": 26,
      "manzil": 7,
      "page": 519,
      "ruku": 453,
      "hizbQuarter": 208,
      "sajda": false
    },
    {
      "number": 4658,
      "text": "قَالَ لَا تَخْتَصِمُو[s[اْ] لَدَىَّ وَقَ[q:387[دْ] قَدَّمْتُ إِلَيْك[c:12818[ُم ب]ِ[h:12819[ٱ]لْوَع[p[ِي][q[د]ِ",
      "numberInSurah": 28,
      "juz": 26,
      "manzil": 7,
      "page": 519,
      "ruku": 453,
      "hizbQuarter": 208,
      "sajda": false
    },
    {
      "number": 4659,
      "text": "مَا يُبَدَّلُ [h:12820[ٱ]لْقَوْلُ لَدَىَّ وَم[o[َآ] أَنَا۟ بِظَلَّ[n[ـٰ][u:2466[مٍ ل]ِّلْعَب[p[ِي][q[د]ِ",
      "numberInSurah": 29,
      "juz": 26,
      "manzil": 7,
      "page": 519,
      "ruku": 453,
      "hizbQuarter": 208,
      "sajda": false
    },
    {
      "number": 4660,
      "text": "يَوْمَ نَقُولُ لِجَهَ[g[نّ]َمَ هَلِ [h:12821[ٱ]مْتَلَأْتِ وَتَقُولُ هَلْ م[a:12822[ِن م]َّز[p[ِي][q[د]ٍ",
      "numberInSurah": 30,
      "juz": 26,
      "manzil": 7,
      "page": 519,
      "ruku": 454,
      "hizbQuarter": 208,
      "sajda": false
    },
    {
      "number": 4661,
      "text": "وَأُزْلِفَتِ [h:9791[ٱ]لْجَ[g[نّ]َةُ لِلْمُتَّقِينَ غَيْرَ بَع[p[ِي][q[د]ٍ",
      "numberInSurah": 31,
      "juz": 26,
      "manzil": 7,
      "page": 519,
      "ruku": 454,
      "hizbQuarter": 208,
      "sajda": false
    },
    {
      "number": 4662,
      "text": "هَ[n[ـٰ]ذَا مَا تُوعَدُونَ لِكُلِّ أَوَّابٍ حَف[p[ِي]ظٍ",
      "numberInSurah": 32,
      "juz": 26,
      "manzil": 7,
      "page": 519,
      "ruku": 454,
      "hizbQuarter": 208,
      "sajda": false
    },
    {
      "number": 4663,
      "text": "مَّنْ خَشِىَ [h:12823[ٱ][l[ل]رَّحْمَ[n[ـٰ]نَ بِ[h:13[ٱ]لْغَيْبِ وَج[o[َا]ٓءَ بِقَلْ[a:12824[بٍ م]ُّن[p[ِي][q[ب]ٍ",
      "numberInSurah": 33,
      "juz": 26,
      "manzil": 7,
      "page": 519,
      "ruku": 454,
      "hizbQuarter": 208,
      "sajda": false
    },
    {
      "number": 4664,
      "text": "ٱ[q:7258[دْ]خُلُوهَا بِسَلَ[n[ـٰ][f:12825[مٍ‌ۖ ذ][n[َٲ]لِكَ يَوْمُ [h:12826[ٱ]لْخُل[p[ُو][q[د]ِ",
      "numberInSurah": 34,
      "juz": 26,
      "manzil": 7,
      "page": 519,
      "ruku": 454,
      "hizbQuarter": 208,
      "sajda": false
    },
    {
      "number": 4665,
      "text": "لَه[w:3531[ُم م]َّا يَش[o[َا]ٓءُونَ فِيهَا وَلَدَيْنَا مَز[p[ِي][q[د]ٌ",
      "numberInSurah": 35,
      "juz": 26,
      "manzil": 7,
      "page": 519,
      "ruku": 454,
      "hizbQuarter": 208,
      "sajda": false
    },
    {
      "number": 4666,
      "text": "وَكَمْ أَهْلَكْنَا قَ[q:8394[بْ]لَه[w:8395[ُم م]ِّ[f:3927[ن ق]َرْنٍ هُمْ أَشَدُّ مِنْه[c:12197[ُم ب]َ[q:12198[طْ][f:12827[شًا ف]َنَقَّبُو[s[اْ] فِى [h:2519[ٱ]لْبِلَ[n[ـٰ]دِ هَلْ م[a:7093[ِن م]َّح[p[ِي]صٍ",
      "numberInSurah": 36,
      "juz": 26,
      "manzil": 7,
      "page": 520,
      "ruku": 454,
      "hizbQuarter": 208,
      "sajda": false
    },
    {
      "number": 4667,
      "text": "إِ[g[نّ]َ فِى ذ[n[َٲ]لِكَ لَذِكْرَىٰ لِمَ[f:10739[ن ك]َانَ لَهُ[n[ۥ] قَلْبٌ أَوْ أَلْقَى [h:12828[ٱ][l[ل]سَّمْعَ وَهُوَ شَه[p[ِي][q[د]ٌ",
      "numberInSurah": 37,
      "juz": 26,
      "manzil": 7,
      "page": 520,
      "ruku": 454,
      "hizbQuarter": 208,
      "sajda": false
    },
    {
      "number": 4668,
      "text": "وَلَقَ[q:341[دْ] خَلَ[q:5159[قْ]نَا [h:7298[ٱ][l[ل]سَّمَ[n[ـٰ]و[n[َٲ]تِ وَ[h:1474[ٱ]لْأَرْضَ وَمَا بَيْنَهُمَا فِى سِتَّةِ أَيَّا[a:12829[مٍ و]َمَا مَسَّنَا م[u:12830[ِن ل]ُّغ[p[ُو][q[ب]ٍ",
      "numberInSurah": 38,
      "juz": 26,
      "manzil": 7,
      "page": 520,
      "ruku": 454,
      "hizbQuarter": 208,
      "sajda": false
    },
    {
      "number": 4669,
      "text": "فَ[h:9999[ٱ]صْبِرْ عَلَىٰ مَا يَقُولُونَ وَسَبِّحْ بِحَمْدِ رَبِّكَ قَ[q:3282[بْ]لَ طُلُوعِ [h:8648[ٱ][l[ل]شَّمْسِ وَقَ[q:8649[بْ]لَ [h:12831[ٱ]لْغُر[p[ُو][q[ب]ِ",
      "numberInSurah": 39,
      "juz": 26,
      "manzil": 7,
      "page": 520,
      "ruku": 454,
      "hizbQuarter": 208,
      "sajda": false
    },
    {
      "number": 4670,
      "text": "وَمِنَ [h:7856[ٱ]لَّيْلِ فَسَبِّحْهُ وَأَ[q:12832[دْ]بَ[n[ـٰ]رَ [h:12833[ٱ][l[ل]سُّج[p[ُو][q[د]ِ",
      "numberInSurah": 40,
      "juz": 26,
      "manzil": 7,
      "page": 520,
      "ruku": 454,
      "hizbQuarter": 208,
      "sajda": false
    },
    {
      "number": 4671,
      "text": "وَ[h:9999[ٱ]سْتَمِعْ يَوْمَ يُنَادِ [h:12834[ٱ]لْمُنَادِ م[a:9578[ِن م]َّكَا[f:11053[نٍ ق]َر[p[ِي][q[ب]ٍ",
      "numberInSurah": 41,
      "juz": 26,
      "manzil": 7,
      "page": 520,
      "ruku": 454,
      "hizbQuarter": 208,
      "sajda": false
    },
    {
      "number": 4672,
      "text": "يَوْمَ يَسْمَعُونَ [h:12835[ٱ][l[ل]صَّيْحَةَ بِ[h:370[ٱ]لْحَقِّ‌ۚ ذ[n[َٲ]لِكَ يَوْمُ [h:12836[ٱ]لْخُر[p[ُو][q[ج]ِ",
      "numberInSurah": 42,
      "juz": 26,
      "manzil": 7,
      "page": 520,
      "ruku": 454,
      "hizbQuarter": 208,
      "sajda": false
    },
    {
      "number": 4673,
      "text": "إِ[g[نّ]َا نَحْنُ نُحْى[n[ِۦ] وَنُمِيتُ وَإِلَيْنَا [h:12837[ٱ]لْمَص[p[ِي]رُ",
      "numberInSurah": 43,
      "juz": 26,
      "manzil": 7,
      "page": 520,
      "ruku": 454,
      "hizbQuarter": 208,
      "sajda": false
    },
    {
      "number": 4674,
      "text": "يَوْمَ تَشَقَّقُ [h:12838[ٱ]لْأَرْضُ عَنْهُمْ سِرَا[f:12839[عًا‌ۚ ذ][n[َٲ]لِكَ حَشْرٌ عَلَيْنَا يَس[p[ِي]رٌ",
      "numberInSurah": 44,
      "juz": 26,
      "manzil": 7,
      "page": 520,
      "ruku": 454,
      "hizbQuarter": 208,
      "sajda": false
    },
    {
      "number": 4675,
      "text": "نَّحْنُ أَعْلَمُ بِمَا يَقُولُونَ‌ۖ وَم[o[َآ] أَ[f:169[نت]َ عَلَيْه[c:12840[ِم ب]ِجَبَّا[f:12841[رٍ‌ۖ ف]َذَكِّرْ بِ[h:8623[ٱ]لْقُرْءَانِ م[a:12842[َن ي]َخَافُ وَع[p[ِي][q[د]ِ",
      "numberInSurah": 45,
      "juz": 26,
      "manzil": 7,
      "page": 520,
      "ruku": 454,
      "hizbQuarter": 208,
      "sajda": false
    }
  ],
  "edition": {
    "identifier": "quran-tajweed",
    "language": "ar",
    "name": "القرآن الكريم المجود (ملون) (tajweed)",
    "englishName": "Tajweed",
    "format": "text",
    "type": "quran",
    "direction": "rtl"
  }
}